<entryForm scriptid="custform_148_6125688_sb1_248" standard="STANDARDINVENTORYPARTFORM">
  <name>PE Fixed Asset</name>
  <recordType>INVENTORYITEM</recordType>
  <inactive>F</inactive>
  <preferred>F</preferred>
  <storedWithRecord>F</storedWithRecord>
  <mainFields>
    <fieldGroup scriptid="primaryinformation">
      <label>Información principal</label>
      <visible>T</visible>
      <showTitle>T</showTitle>
      <singleColumn>F</singleColumn>
      <fields position="MIDDLE">
        <field>
          <id>CUSTOMFORM</id>
          <label>Custom Form</label>
          <visible>T</visible>
          <mandatory>F</mandatory>
          <displayType>NORMAL</displayType>
          <columnBreak>F</columnBreak>
          <sameRowAsPrevious>F</sameRowAsPrevious>
        </field>
        <field>
          <id>INTERNALID</id>
          <label>Internal ID</label>
          <visible>T</visible>
          <mandatory>F</mandatory>
          <displayType>NORMAL</displayType>
          <columnBreak>F</columnBreak>
          <sameRowAsPrevious>F</sameRowAsPrevious>
        </field>
        <field>
          <id>ITEMID</id>
          <label>Item Name/Number</label>
          <visible>T</visible>
          <mandatory>T</mandatory>
          <displayType>NORMAL</displayType>
          <columnBreak>F</columnBreak>
          <sameRowAsPrevious>F</sameRowAsPrevious>
        </field>
        <field>
          <id>DISPLAYNAME</id>
          <label>Display Name/Code</label>
          <visible>T</visible>
          <mandatory>T</mandatory>
          <displayType>NORMAL</displayType>
          <columnBreak>F</columnBreak>
          <sameRowAsPrevious>F</sameRowAsPrevious>
        </field>
        <field>
          <id>BASEUNIT</id>
          <label>Primary Base Unit</label>
          <visible>T</visible>
          <mandatory>F</mandatory>
          <displayType>NORMAL</displayType>
          <columnBreak>F</columnBreak>
          <sameRowAsPrevious>F</sameRowAsPrevious>
        </field>
        <field>
          <id>UPCCODE</id>
          <label>UPC Code</label>
          <visible>F</visible>
          <mandatory>F</mandatory>
          <displayType>NORMAL</displayType>
          <columnBreak>F</columnBreak>
          <sameRowAsPrevious>F</sameRowAsPrevious>
        </field>
        <field>
          <id>UNITSTYPE</id>
          <label>Primary Units Type</label>
          <visible>T</visible>
          <mandatory>T</mandatory>
          <displayType>NORMAL</displayType>
          <columnBreak>F</columnBreak>
          <sameRowAsPrevious>F</sameRowAsPrevious>
        </field>
        <field>
          <id>PARENT</id>
          <label>Subitem of</label>
          <visible>F</visible>
          <mandatory>F</mandatory>
          <displayType>NORMAL</displayType>
          <columnBreak>F</columnBreak>
          <sameRowAsPrevious>F</sameRowAsPrevious>
        </field>
        <field>
          <id>CONSUMPTIONUNIT</id>
          <label>Primary Consumption Unit</label>
          <visible>T</visible>
          <mandatory>F</mandatory>
          <displayType>NORMAL</displayType>
          <columnBreak>F</columnBreak>
          <sameRowAsPrevious>F</sameRowAsPrevious>
        </field>
        <field>
          <id>VENDORNAME</id>
          <label>Vendor Name/Code</label>
          <visible>T</visible>
          <mandatory>F</mandatory>
          <displayType>NORMAL</displayType>
          <columnBreak>F</columnBreak>
          <sameRowAsPrevious>F</sameRowAsPrevious>
        </field>
        <field>
          <id>ISINACTIVE</id>
          <label>Inactive</label>
          <visible>T</visible>
          <mandatory>F</mandatory>
          <displayType>NORMAL</displayType>
          <columnBreak>F</columnBreak>
          <sameRowAsPrevious>F</sameRowAsPrevious>
        </field>
      </fields>
    </fieldGroup>
    <fieldGroup scriptid="classification">
      <label>Clasificación</label>
      <visible>T</visible>
      <showTitle>T</showTitle>
      <singleColumn>F</singleColumn>
      <fields position="MIDDLE">
        <field>
          <id>SUBSIDIARY</id>
          <label>Subsidiary</label>
          <visible>T</visible>
          <mandatory>F</mandatory>
          <displayType>NORMAL</displayType>
          <columnBreak>F</columnBreak>
          <sameRowAsPrevious>F</sameRowAsPrevious>
        </field>
        <field>
          <id>DEPARTMENT</id>
          <label>Department</label>
          <visible>T</visible>
          <mandatory>T</mandatory>
          <displayType>NORMAL</displayType>
          <columnBreak>F</columnBreak>
          <sameRowAsPrevious>F</sameRowAsPrevious>
        </field>
        <field>
          <id>CLASS</id>
          <label>Class</label>
          <visible>T</visible>
          <mandatory>T</mandatory>
          <displayType>NORMAL</displayType>
          <columnBreak>F</columnBreak>
          <sameRowAsPrevious>F</sameRowAsPrevious>
        </field>
        <field>
          <id>LOCATION</id>
          <label>Location</label>
          <visible>T</visible>
          <mandatory>F</mandatory>
          <displayType>NORMAL</displayType>
          <columnBreak>F</columnBreak>
          <sameRowAsPrevious>F</sameRowAsPrevious>
        </field>
      </fields>
    </fieldGroup>
    <defaultFieldGroup/>
  </mainFields>
  <tabs>
    <tab>
      <id>[scriptid=custtab_pe_tab]</id>
      <label>PE Localization</label>
      <visible>T</visible>
      <fieldGroups>
        <defaultFieldGroup>
          <fields position="MIDDLE">
            <field>
              <id>[scriptid=custitem_pe_valuation_method]</id>
              <label>PE Valuation Method New</label>
              <visible>T</visible>
              <mandatory>T</mandatory>
              <displayType>NORMAL</displayType>
              <columnBreak>F</columnBreak>
              <sameRowAsPrevious>F</sameRowAsPrevious>
            </field>
            <field>
              <id>[scriptid=custitem_pe_cod_valuation_method]</id>
              <label> PE Cod Valuation Method 3</label>
              <visible>T</visible>
              <mandatory>F</mandatory>
              <displayType>NORMAL</displayType>
              <columnBreak>F</columnBreak>
              <sameRowAsPrevious>F</sameRowAsPrevious>
            </field>
            <field>
              <id>[scriptid=custitem_pe_existence_type]</id>
              <label>PE Existence Type</label>
              <visible>T</visible>
              <mandatory>T</mandatory>
              <displayType>NORMAL</displayType>
              <columnBreak>F</columnBreak>
              <sameRowAsPrevious>F</sameRowAsPrevious>
            </field>
            <field>
              <id>[scriptid=custitem_pe_cod_existence_type]</id>
              <label>PE Cod Existence Type</label>
              <visible>T</visible>
              <mandatory>F</mandatory>
              <displayType>DISABLED</displayType>
              <columnBreak>F</columnBreak>
              <sameRowAsPrevious>F</sameRowAsPrevious>
            </field>
            <field>
              <id>[scriptid=custitem_pe_measurement_unit]</id>
              <label>PE Measurement Unit 2</label>
              <visible>T</visible>
              <mandatory>T</mandatory>
              <displayType>NORMAL</displayType>
              <columnBreak>F</columnBreak>
              <sameRowAsPrevious>F</sameRowAsPrevious>
            </field>
            <field>
              <id>[scriptid=custitem_pe_cod_measure_unit]</id>
              <label>PE Cod Measure Unit</label>
              <visible>T</visible>
              <mandatory>F</mandatory>
              <displayType>DISABLED</displayType>
              <columnBreak>T</columnBreak>
              <sameRowAsPrevious>F</sameRowAsPrevious>
            </field>
            <field>
              <id>[scriptid=custitem_pe_inventory_catalog]</id>
              <label>PE Inventory Catalog</label>
              <visible>T</visible>
              <mandatory>T</mandatory>
              <displayType>NORMAL</displayType>
              <columnBreak>F</columnBreak>
              <sameRowAsPrevious>F</sameRowAsPrevious>
            </field>
            <field>
              <id>[scriptid=custitem_pe_cod_inventory_catalog]</id>
              <label>PE Cod Inventory Catalog</label>
              <visible>T</visible>
              <mandatory>F</mandatory>
              <displayType>DISABLED</displayType>
              <columnBreak>F</columnBreak>
              <sameRowAsPrevious>F</sameRowAsPrevious>
            </field>
            <field>
              <id>[scriptid=custitem_pe_cod_cubso]</id>
              <label>PE Cod CUBSO</label>
              <visible>T</visible>
              <mandatory>F</mandatory>
              <displayType>NORMAL</displayType>
              <columnBreak>F</columnBreak>
              <sameRowAsPrevious>F</sameRowAsPrevious>
            </field>
            <field>
              <id>[scriptid=custitem_pe_consignacion]</id>
              <label>PE Consignacion</label>
              <visible>T</visible>
              <mandatory>F</mandatory>
              <displayType>NORMAL</displayType>
              <columnBreak>F</columnBreak>
              <sameRowAsPrevious>F</sameRowAsPrevious>
            </field>
            <field>
              <id>[scriptid=custitem_pe_inventory_usage]</id>
              <label>PE Inventory Usage</label>
              <visible>T</visible>
              <mandatory>F</mandatory>
              <displayType>NORMAL</displayType>
              <columnBreak>T</columnBreak>
              <sameRowAsPrevious>F</sameRowAsPrevious>
            </field>
            <field>
              <id>[scriptid=custitem_pe_is_icbp]</id>
              <label>PE is ICBP</label>
              <visible>T</visible>
              <mandatory>F</mandatory>
              <displayType>NORMAL</displayType>
              <columnBreak>F</columnBreak>
              <sameRowAsPrevious>F</sameRowAsPrevious>
            </field>
            <field>
              <id>[scriptid=custitem_pe_is_anticipo]</id>
              <label>PE is Anticipo</label>
              <visible>T</visible>
              <mandatory>F</mandatory>
              <displayType>NORMAL</displayType>
              <columnBreak>F</columnBreak>
              <sameRowAsPrevious>F</sameRowAsPrevious>
            </field>
            <field>
              <id>[scriptid=custitem_pe_purchase_account]</id>
              <label>PE Purchase Account (60)</label>
              <visible>F</visible>
              <mandatory>F</mandatory>
              <displayType>NORMAL</displayType>
              <columnBreak>F</columnBreak>
              <sameRowAsPrevious>F</sameRowAsPrevious>
            </field>
            <field>
              <id>[scriptid=custitem_pe_variation_account]</id>
              <label>PE Variation Account (61)</label>
              <visible>F</visible>
              <mandatory>F</mandatory>
              <displayType>NORMAL</displayType>
              <columnBreak>F</columnBreak>
              <sameRowAsPrevious>F</sameRowAsPrevious>
            </field>
          </fields>
        </defaultFieldGroup>
      </fieldGroups>
      <subItems/>
    </tab>
    <tab>
      <id>ITEMINVENTORY</id>
      <label>Purchasing/Inventory</label>
      <visible>T</visible>
      <fieldGroups>
        <fieldGroup scriptid="itemcostdetail">
          <label>Detalle de artículo/costo</label>
          <visible>T</visible>
          <showTitle>T</showTitle>
          <singleColumn>F</singleColumn>
          <fields position="MIDDLE">
            <field>
              <id>PURCHASEDESCRIPTION</id>
              <label>Purchase Description</label>
              <visible>T</visible>
              <mandatory>F</mandatory>
              <displayType>NORMAL</displayType>
              <columnBreak>F</columnBreak>
              <sameRowAsPrevious>F</sameRowAsPrevious>
            </field>
            <field>
              <id>COSTINGMETHOD</id>
              <label>Costing Method</label>
              <visible>T</visible>
              <mandatory>F</mandatory>
              <displayType>NORMAL</displayType>
              <columnBreak>F</columnBreak>
              <sameRowAsPrevious>F</sameRowAsPrevious>
            </field>
            <field>
              <id>TOTALVALUE</id>
              <label>Total Value</label>
              <visible>F</visible>
              <mandatory>F</mandatory>
              <displayType>NORMAL</displayType>
              <columnBreak>F</columnBreak>
              <sameRowAsPrevious>F</sameRowAsPrevious>
            </field>
            <field>
              <id>COST</id>
              <label>Purchase Price</label>
              <visible>T</visible>
              <mandatory>F</mandatory>
              <displayType>NORMAL</displayType>
              <columnBreak>F</columnBreak>
              <sameRowAsPrevious>F</sameRowAsPrevious>
            </field>
            <field>
              <id>TOTALQUANTITYONHAND</id>
              <label>Total Quantity On Hand</label>
              <visible>T</visible>
              <mandatory>F</mandatory>
              <displayType>NORMAL</displayType>
              <columnBreak>F</columnBreak>
              <sameRowAsPrevious>F</sameRowAsPrevious>
            </field>
            <field>
              <id>AVERAGECOST</id>
              <label>Average Cost</label>
              <visible>T</visible>
              <mandatory>F</mandatory>
              <displayType>NORMAL</displayType>
              <columnBreak>F</columnBreak>
              <sameRowAsPrevious>F</sameRowAsPrevious>
            </field>
            <field>
              <id>LASTPURCHASEPRICE</id>
              <label>Last Purchase Price</label>
              <visible>F</visible>
              <mandatory>F</mandatory>
              <displayType>NORMAL</displayType>
              <columnBreak>F</columnBreak>
              <sameRowAsPrevious>F</sameRowAsPrevious>
            </field>
            <field>
              <id>STOCKDESCRIPTION</id>
              <label>Stock Description</label>
              <visible>F</visible>
              <mandatory>F</mandatory>
              <displayType>NORMAL</displayType>
              <columnBreak>F</columnBreak>
              <sameRowAsPrevious>F</sameRowAsPrevious>
            </field>
            <field>
              <id>MATCHBILLTORECEIPT</id>
              <label>Match Bill To Receipt</label>
              <visible>F</visible>
              <mandatory>F</mandatory>
              <displayType>NORMAL</displayType>
              <columnBreak>F</columnBreak>
              <sameRowAsPrevious>F</sameRowAsPrevious>
            </field>
            <field>
              <id>DEFAULTRETURNCOST</id>
              <label>Default Return Cost</label>
              <visible>F</visible>
              <mandatory>F</mandatory>
              <displayType>NORMAL</displayType>
              <columnBreak>F</columnBreak>
              <sameRowAsPrevious>F</sameRowAsPrevious>
            </field>
            <field>
              <id>TRACKLANDEDCOST</id>
              <label>Track Landed Cost</label>
              <visible>T</visible>
              <mandatory>F</mandatory>
              <displayType>NORMAL</displayType>
              <columnBreak>F</columnBreak>
              <sameRowAsPrevious>F</sameRowAsPrevious>
            </field>
          </fields>
        </fieldGroup>
        <fieldGroup scriptid="inventorymanagement">
          <label>Gestión de inventario</label>
          <visible>T</visible>
          <showTitle>T</showTitle>
          <singleColumn>F</singleColumn>
          <fields position="MIDDLE">
            <field>
              <id>PREFERREDSTOCKLEVEL</id>
              <label>Preferred Stock Level</label>
              <visible>T</visible>
              <mandatory>F</mandatory>
              <displayType>NORMAL</displayType>
              <columnBreak>F</columnBreak>
              <sameRowAsPrevious>F</sameRowAsPrevious>
            </field>
            <field>
              <id>AUTOPREFERREDSTOCKLEVEL</id>
              <label>Auto-Calculate</label>
              <visible>T</visible>
              <mandatory>F</mandatory>
              <displayType>NORMAL</displayType>
              <columnBreak>F</columnBreak>
              <sameRowAsPrevious>T</sameRowAsPrevious>
            </field>
            <field>
              <id>PREFERREDSTOCKLEVELDAYS</id>
              <label>Days</label>
              <visible>T</visible>
              <mandatory>F</mandatory>
              <displayType>NORMAL</displayType>
              <columnBreak>F</columnBreak>
              <sameRowAsPrevious>T</sameRowAsPrevious>
            </field>
            <field>
              <id>SAFETYSTOCKLEVEL</id>
              <label>Safety Stock Level</label>
              <visible>T</visible>
              <mandatory>F</mandatory>
              <displayType>NORMAL</displayType>
              <columnBreak>F</columnBreak>
              <sameRowAsPrevious>F</sameRowAsPrevious>
            </field>
            <field>
              <id>SAFETYSTOCKLEVELDAYS</id>
              <label>Days</label>
              <visible>T</visible>
              <mandatory>F</mandatory>
              <displayType>NORMAL</displayType>
              <columnBreak>F</columnBreak>
              <sameRowAsPrevious>T</sameRowAsPrevious>
            </field>
            <field>
              <id>REORDERPOINT</id>
              <label>Reorder Point</label>
              <visible>T</visible>
              <mandatory>F</mandatory>
              <displayType>NORMAL</displayType>
              <columnBreak>F</columnBreak>
              <sameRowAsPrevious>F</sameRowAsPrevious>
            </field>
            <field>
              <id>AUTOREORDERPOINT</id>
              <label>Auto-Calculate</label>
              <visible>T</visible>
              <mandatory>F</mandatory>
              <displayType>NORMAL</displayType>
              <columnBreak>F</columnBreak>
              <sameRowAsPrevious>T</sameRowAsPrevious>
            </field>
            <field>
              <id>REORDERMULTIPLE</id>
              <label>Reorder Multiple</label>
              <visible>T</visible>
              <mandatory>F</mandatory>
              <displayType>NORMAL</displayType>
              <columnBreak>F</columnBreak>
              <sameRowAsPrevious>F</sameRowAsPrevious>
            </field>
            <field>
              <id>LEADTIME</id>
              <label>Purchase Lead Time</label>
              <visible>T</visible>
              <mandatory>F</mandatory>
              <displayType>NORMAL</displayType>
              <columnBreak>F</columnBreak>
              <sameRowAsPrevious>F</sameRowAsPrevious>
            </field>
            <field>
              <id>AUTOLEADTIME</id>
              <label>Auto-Calculate</label>
              <visible>T</visible>
              <mandatory>F</mandatory>
              <displayType>NORMAL</displayType>
              <columnBreak>F</columnBreak>
              <sameRowAsPrevious>T</sameRowAsPrevious>
            </field>
            <field>
              <id>SEASONALDEMAND</id>
              <label>Seasonal Demand</label>
              <visible>F</visible>
              <mandatory>F</mandatory>
              <displayType>NORMAL</displayType>
              <columnBreak>F</columnBreak>
              <sameRowAsPrevious>F</sameRowAsPrevious>
            </field>
            <field>
              <id>COSTACCOUNTINGSTATUS</id>
              <label>Cost Accounting Status</label>
              <visible>F</visible>
              <mandatory>F</mandatory>
              <displayType>NORMAL</displayType>
              <columnBreak>F</columnBreak>
              <sameRowAsPrevious>F</sameRowAsPrevious>
            </field>
            <field>
              <id>DEMANDMODIFIER</id>
              <label>Expected Demand Change</label>
              <visible>F</visible>
              <mandatory>F</mandatory>
              <displayType>NORMAL</displayType>
              <columnBreak>F</columnBreak>
              <sameRowAsPrevious>F</sameRowAsPrevious>
            </field>
            <field>
              <id>QUANTITYONHAND</id>
              <label>Quantity On Hand</label>
              <visible>T</visible>
              <mandatory>F</mandatory>
              <displayType>NORMAL</displayType>
              <columnBreak>F</columnBreak>
              <sameRowAsPrevious>F</sameRowAsPrevious>
            </field>
            <field>
              <id>QUANTITYCOMMITTED</id>
              <label>Quantity Committed</label>
              <visible>T</visible>
              <mandatory>F</mandatory>
              <displayType>NORMAL</displayType>
              <columnBreak>F</columnBreak>
              <sameRowAsPrevious>F</sameRowAsPrevious>
            </field>
            <field>
              <id>QUANTITYAVAILABLE</id>
              <label>Quantity Available</label>
              <visible>T</visible>
              <mandatory>F</mandatory>
              <displayType>NORMAL</displayType>
              <columnBreak>F</columnBreak>
              <sameRowAsPrevious>F</sameRowAsPrevious>
            </field>
            <field>
              <id>QUANTITYBACKORDERED</id>
              <label>Quantity Back Ordered</label>
              <visible>T</visible>
              <mandatory>F</mandatory>
              <displayType>NORMAL</displayType>
              <columnBreak>F</columnBreak>
              <sameRowAsPrevious>F</sameRowAsPrevious>
            </field>
            <field>
              <id>QUANTITYONORDER</id>
              <label>Quantity On Order</label>
              <visible>T</visible>
              <mandatory>F</mandatory>
              <displayType>NORMAL</displayType>
              <columnBreak>F</columnBreak>
              <sameRowAsPrevious>F</sameRowAsPrevious>
            </field>
            <field>
              <id>TRANSFERPRICE</id>
              <label>Transfer Price</label>
              <visible>T</visible>
              <mandatory>F</mandatory>
              <displayType>NORMAL</displayType>
              <columnBreak>F</columnBreak>
              <sameRowAsPrevious>F</sameRowAsPrevious>
            </field>
            <field>
              <id>USEBINS</id>
              <label>Use Bins</label>
              <visible>T</visible>
              <mandatory>F</mandatory>
              <displayType>NORMAL</displayType>
              <columnBreak>F</columnBreak>
              <sameRowAsPrevious>F</sameRowAsPrevious>
            </field>
          </fields>
        </fieldGroup>
        <fieldGroup scriptid="manufacturing">
          <label>Fabricación</label>
          <visible>T</visible>
          <showTitle>T</showTitle>
          <singleColumn>F</singleColumn>
          <fields position="MIDDLE">
            <field>
              <id>MANUFACTURER</id>
              <label>Manufacturer</label>
              <visible>T</visible>
              <mandatory>F</mandatory>
              <displayType>NORMAL</displayType>
              <columnBreak>F</columnBreak>
              <sameRowAsPrevious>F</sameRowAsPrevious>
            </field>
            <field>
              <id>MPN</id>
              <label>MPN</label>
              <visible>T</visible>
              <mandatory>F</mandatory>
              <displayType>NORMAL</displayType>
              <columnBreak>F</columnBreak>
              <sameRowAsPrevious>F</sameRowAsPrevious>
            </field>
            <field>
              <id>COUNTRYOFMANUFACTURE</id>
              <label>Manufacturer Country</label>
              <visible>F</visible>
              <mandatory>F</mandatory>
              <displayType>NORMAL</displayType>
              <columnBreak>F</columnBreak>
              <sameRowAsPrevious>F</sameRowAsPrevious>
            </field>
            <field>
              <id>PRODUCER</id>
              <label>Producer</label>
              <visible>T</visible>
              <mandatory>F</mandatory>
              <displayType>NORMAL</displayType>
              <columnBreak>F</columnBreak>
              <sameRowAsPrevious>F</sameRowAsPrevious>
            </field>
            <field>
              <id>MANUFACTURERADDR1</id>
              <label>Manufacturer Address</label>
              <visible>F</visible>
              <mandatory>F</mandatory>
              <displayType>NORMAL</displayType>
              <columnBreak>F</columnBreak>
              <sameRowAsPrevious>F</sameRowAsPrevious>
            </field>
            <field>
              <id>MANUFACTURERCITY</id>
              <label>Manufacturer City</label>
              <visible>F</visible>
              <mandatory>F</mandatory>
              <displayType>NORMAL</displayType>
              <columnBreak>F</columnBreak>
              <sameRowAsPrevious>F</sameRowAsPrevious>
            </field>
            <field>
              <id>MANUFACTURERSTATE</id>
              <label>Manufacturer State</label>
              <visible>F</visible>
              <mandatory>F</mandatory>
              <displayType>NORMAL</displayType>
              <columnBreak>F</columnBreak>
              <sameRowAsPrevious>F</sameRowAsPrevious>
            </field>
            <field>
              <id>MANUFACTURERZIP</id>
              <label>Manufacturer Zip</label>
              <visible>F</visible>
              <mandatory>F</mandatory>
              <displayType>NORMAL</displayType>
              <columnBreak>F</columnBreak>
              <sameRowAsPrevious>F</sameRowAsPrevious>
            </field>
            <field>
              <id>MANUFACTURERTAXID</id>
              <label>Manufacturer Tax Id</label>
              <visible>F</visible>
              <mandatory>F</mandatory>
              <displayType>NORMAL</displayType>
              <columnBreak>F</columnBreak>
              <sameRowAsPrevious>F</sameRowAsPrevious>
            </field>
            <field>
              <id>MANUFACTURERTARIFF</id>
              <label>Manufacturer Tariff</label>
              <visible>F</visible>
              <mandatory>F</mandatory>
              <displayType>NORMAL</displayType>
              <columnBreak>F</columnBreak>
              <sameRowAsPrevious>F</sameRowAsPrevious>
            </field>
          </fields>
        </fieldGroup>
        <fieldGroup scriptid="vendorbillmatching">
          <label>Confrontación de factura de proveedor</label>
          <visible>T</visible>
          <showTitle>T</showTitle>
          <singleColumn>F</singleColumn>
          <fields position="MIDDLE">
            <field>
              <id>PURCHASEORDERQUANTITY</id>
              <label>Purchase Order Quantity Tolerance</label>
              <visible>F</visible>
              <mandatory>F</mandatory>
              <displayType>NORMAL</displayType>
              <columnBreak>F</columnBreak>
              <sameRowAsPrevious>F</sameRowAsPrevious>
            </field>
            <field>
              <id>PURCHASEORDERAMOUNT</id>
              <label>Purchase Order Amount Tolerance</label>
              <visible>F</visible>
              <mandatory>F</mandatory>
              <displayType>NORMAL</displayType>
              <columnBreak>F</columnBreak>
              <sameRowAsPrevious>F</sameRowAsPrevious>
            </field>
            <field>
              <id>PURCHASEORDERQUANTITYDIFF</id>
              <label>Purchase Order Quantity Difference</label>
              <visible>F</visible>
              <mandatory>F</mandatory>
              <displayType>NORMAL</displayType>
              <columnBreak>F</columnBreak>
              <sameRowAsPrevious>F</sameRowAsPrevious>
            </field>
            <field>
              <id>RECEIPTQUANTITY</id>
              <label>Item Receipt Quantity Tolerance</label>
              <visible>F</visible>
              <mandatory>F</mandatory>
              <displayType>NORMAL</displayType>
              <columnBreak>F</columnBreak>
              <sameRowAsPrevious>F</sameRowAsPrevious>
            </field>
            <field>
              <id>RECEIPTAMOUNT</id>
              <label>Item Receipt Amount Tolerance</label>
              <visible>F</visible>
              <mandatory>F</mandatory>
              <displayType>NORMAL</displayType>
              <columnBreak>F</columnBreak>
              <sameRowAsPrevious>F</sameRowAsPrevious>
            </field>
            <field>
              <id>RECEIPTQUANTITYDIFF</id>
              <label>Item Receipt Quantity Difference</label>
              <visible>F</visible>
              <mandatory>F</mandatory>
              <displayType>NORMAL</displayType>
              <columnBreak>F</columnBreak>
              <sameRowAsPrevious>F</sameRowAsPrevious>
            </field>
          </fields>
        </fieldGroup>
        <defaultFieldGroup>
          <fields position="MIDDLE">
            <field>
              <id>SERIALNUMBERS</id>
              <label>Serial/Lot Numbers</label>
              <visible>T</visible>
              <mandatory>F</mandatory>
              <displayType>NORMAL</displayType>
              <columnBreak>F</columnBreak>
              <sameRowAsPrevious>F</sameRowAsPrevious>
            </field>
          </fields>
        </defaultFieldGroup>
      </fieldGroups>
      <subItems>
        <subList>
          <id>ITEMNUMBERS</id>
          <label>Inventory Numbers</label>
          <visible>T</visible>
          <neverEmpty>F</neverEmpty>
        </subList>
        <subTab>
          <id>ITEMLOCATIONS</id>
          <label>Locations</label>
          <visible>T</visible>
          <fieldGroups>
            <defaultFieldGroup>
              <fields position="MIDDLE">
                <field>
                  <id>PREFERREDLOCATION</id>
                  <label>Preferred Location</label>
                  <visible>T</visible>
                  <mandatory>F</mandatory>
                  <displayType>NORMAL</displayType>
                  <columnBreak>F</columnBreak>
                  <sameRowAsPrevious>F</sameRowAsPrevious>
                </field>
              </fields>
            </defaultFieldGroup>
          </fieldGroups>
          <subLists>
            <subList>
              <id>ITEMLOCATIONS</id>
              <label>Locations</label>
              <visible>T</visible>
              <neverEmpty>F</neverEmpty>
            </subList>
          </subLists>
        </subTab>
        <subList>
          <id>ITEMBINNUMBER</id>
          <label>Bin Numbers</label>
          <visible>T</visible>
          <neverEmpty>F</neverEmpty>
        </subList>
        <subTab>
          <id>ITEMVENDORS</id>
          <label>Vendors</label>
          <visible>T</visible>
          <fieldGroups>
            <defaultFieldGroup/>
          </fieldGroups>
          <subLists>
            <subList>
              <id>ITEMITEMVENDOR</id>
              <label>Vendors</label>
              <visible>T</visible>
              <neverEmpty>F</neverEmpty>
            </subList>
          </subLists>
        </subTab>
      </subItems>
    </tab>
    <tab>
      <id>ITEMINVENTORYDETAIL</id>
      <label>Inventory Detail</label>
      <visible>T</visible>
      <fieldGroups>
        <defaultFieldGroup/>
      </fieldGroups>
      <subItems>
        <subList>
          <id>ITEMINVENTORYDETAILSRCH</id>
          <label>Inventory Detail</label>
          <visible>T</visible>
          <neverEmpty>F</neverEmpty>
        </subList>
        <subList>
          <id>ITEMBINNUMBERSEARCH</id>
          <label>Bin Numbers</label>
          <visible>T</visible>
          <neverEmpty>F</neverEmpty>
        </subList>
        <subList>
          <id>ITEMINVENTORYNUMBERSRCH</id>
          <label>Inventory Numbers</label>
          <visible>T</visible>
          <neverEmpty>F</neverEmpty>
        </subList>
        <subList>
          <id>ITEMINVENTORYSTATUSSRCH</id>
          <label>Inventory Statuses</label>
          <visible>T</visible>
          <neverEmpty>F</neverEmpty>
        </subList>
      </subItems>
    </tab>
    <tab>
      <id>ITEMPRICING</id>
      <label>Sales / Pricing</label>
      <visible>T</visible>
      <fieldGroups>
        <fieldGroup scriptid="sales">
          <label>Ventas</label>
          <visible>T</visible>
          <showTitle>T</showTitle>
          <singleColumn>F</singleColumn>
          <fields position="MIDDLE">
            <field>
              <id>RATE</id>
              <label>Sales Price (Rate)</label>
              <visible>T</visible>
              <mandatory>F</mandatory>
              <displayType>NORMAL</displayType>
              <columnBreak>F</columnBreak>
              <sameRowAsPrevious>F</sameRowAsPrevious>
            </field>
            <field>
              <id>SALESDESCRIPTION</id>
              <label>Sales Description</label>
              <visible>T</visible>
              <mandatory>F</mandatory>
              <displayType>NORMAL</displayType>
              <columnBreak>F</columnBreak>
              <sameRowAsPrevious>F</sameRowAsPrevious>
            </field>
            <field>
              <id>COSTESTIMATETYPE</id>
              <label>Cost Estimate Type</label>
              <visible>T</visible>
              <mandatory>F</mandatory>
              <displayType>NORMAL</displayType>
              <columnBreak>F</columnBreak>
              <sameRowAsPrevious>F</sameRowAsPrevious>
            </field>
            <field>
              <id>COSTESTIMATE</id>
              <label>Item Defined Cost</label>
              <visible>T</visible>
              <mandatory>F</mandatory>
              <displayType>NORMAL</displayType>
              <columnBreak>F</columnBreak>
              <sameRowAsPrevious>F</sameRowAsPrevious>
            </field>
            <field>
              <id>MINIMUMQUANTITY</id>
              <label>Minimum Quantity</label>
              <visible>T</visible>
              <mandatory>F</mandatory>
              <displayType>NORMAL</displayType>
              <columnBreak>F</columnBreak>
              <sameRowAsPrevious>F</sameRowAsPrevious>
            </field>
            <field>
              <id>MAXIMUMQUANTITY</id>
              <label>Maximum Quantity</label>
              <visible>T</visible>
              <mandatory>F</mandatory>
              <displayType>NORMAL</displayType>
              <columnBreak>F</columnBreak>
              <sameRowAsPrevious>F</sameRowAsPrevious>
            </field>
            <field>
              <id>ENFORCEMINQTYINTERNALLY</id>
              <label>Enforce Minimum Internally</label>
              <visible>T</visible>
              <mandatory>F</mandatory>
              <displayType>NORMAL</displayType>
              <columnBreak>F</columnBreak>
              <sameRowAsPrevious>T</sameRowAsPrevious>
            </field>
          </fields>
        </fieldGroup>
        <fieldGroup scriptid="pricingshipping">
          <label>Envío</label>
          <visible>T</visible>
          <showTitle>T</showTitle>
          <singleColumn>F</singleColumn>
          <fields position="MIDDLE">
            <field>
              <id>WEIGHT</id>
              <label>Item Weight</label>
              <visible>F</visible>
              <mandatory>F</mandatory>
              <displayType>NORMAL</displayType>
              <columnBreak>F</columnBreak>
              <sameRowAsPrevious>F</sameRowAsPrevious>
            </field>
            <field>
              <id>SHIPPACKAGE</id>
              <label>Package</label>
              <visible>F</visible>
              <mandatory>F</mandatory>
              <displayType>NORMAL</displayType>
              <columnBreak>F</columnBreak>
              <sameRowAsPrevious>F</sameRowAsPrevious>
            </field>
            <field>
              <id>SHIPINDIVIDUALLY</id>
              <label>Ships Individually</label>
              <visible>T</visible>
              <mandatory>F</mandatory>
              <displayType>NORMAL</displayType>
              <columnBreak>F</columnBreak>
              <sameRowAsPrevious>F</sameRowAsPrevious>
            </field>
            <field>
              <id>SHIPPINGCOST</id>
              <label>Shipping Cost</label>
              <visible>T</visible>
              <mandatory>F</mandatory>
              <displayType>NORMAL</displayType>
              <columnBreak>F</columnBreak>
              <sameRowAsPrevious>F</sameRowAsPrevious>
            </field>
            <field>
              <id>HANDLINGCOST</id>
              <label>Handling Cost</label>
              <visible>T</visible>
              <mandatory>F</mandatory>
              <displayType>NORMAL</displayType>
              <columnBreak>F</columnBreak>
              <sameRowAsPrevious>F</sameRowAsPrevious>
            </field>
            <field>
              <id>PREFERENCECRITERION</id>
              <label>Preference Criterion</label>
              <visible>T</visible>
              <mandatory>F</mandatory>
              <displayType>NORMAL</displayType>
              <columnBreak>F</columnBreak>
              <sameRowAsPrevious>F</sameRowAsPrevious>
            </field>
            <field>
              <id>SCHEDULEBNUMBER</id>
              <label>Schedule B Number</label>
              <visible>F</visible>
              <mandatory>F</mandatory>
              <displayType>NORMAL</displayType>
              <columnBreak>F</columnBreak>
              <sameRowAsPrevious>F</sameRowAsPrevious>
            </field>
            <field>
              <id>SCHEDULEBQUANTITY</id>
              <label>Schedule B Quantity</label>
              <visible>T</visible>
              <mandatory>F</mandatory>
              <displayType>NORMAL</displayType>
              <columnBreak>F</columnBreak>
              <sameRowAsPrevious>F</sameRowAsPrevious>
            </field>
            <field>
              <id>SCHEDULEBCODE</id>
              <label>Schedule B Code</label>
              <visible>T</visible>
              <mandatory>F</mandatory>
              <displayType>NORMAL</displayType>
              <columnBreak>F</columnBreak>
              <sameRowAsPrevious>F</sameRowAsPrevious>
            </field>
          </fields>
        </fieldGroup>
        <fieldGroup scriptid="pricing">
          <label>Fijación de precios</label>
          <visible>T</visible>
          <showTitle>T</showTitle>
          <singleColumn>F</singleColumn>
          <fields position="MIDDLE">
            <field>
              <id>QUANTITYPRICINGSCHEDULE</id>
              <label>Quantity Pricing Schedule</label>
              <visible>T</visible>
              <mandatory>F</mandatory>
              <displayType>NORMAL</displayType>
              <columnBreak>F</columnBreak>
              <sameRowAsPrevious>F</sameRowAsPrevious>
            </field>
            <field>
              <id>USEMARGINALRATES</id>
              <label>Use Marginal Rates</label>
              <visible>T</visible>
              <mandatory>F</mandatory>
              <displayType>NORMAL</displayType>
              <columnBreak>F</columnBreak>
              <sameRowAsPrevious>F</sameRowAsPrevious>
            </field>
            <field>
              <id>OVERALLQUANTITYPRICINGTYPE</id>
              <label>Calculate Quantity Discounts</label>
              <visible>T</visible>
              <mandatory>F</mandatory>
              <displayType>NORMAL</displayType>
              <columnBreak>F</columnBreak>
              <sameRowAsPrevious>F</sameRowAsPrevious>
            </field>
            <field>
              <id>PRICINGGROUP</id>
              <label>Pricing Group</label>
              <visible>T</visible>
              <mandatory>F</mandatory>
              <displayType>NORMAL</displayType>
              <columnBreak>F</columnBreak>
              <sameRowAsPrevious>F</sameRowAsPrevious>
            </field>
          </fields>
        </fieldGroup>
        <defaultFieldGroup>
          <fields position="MIDDLE">
            <field>
              <id>BILLINGSCHEDULE</id>
              <label>Billing Schedule</label>
              <visible>T</visible>
              <mandatory>F</mandatory>
              <displayType>NORMAL</displayType>
              <columnBreak>F</columnBreak>
              <sameRowAsPrevious>F</sameRowAsPrevious>
            </field>
            <field>
              <id>FRAUDRISK</id>
              <label>Fraud Risk</label>
              <visible>F</visible>
              <mandatory>F</mandatory>
              <displayType>NORMAL</displayType>
              <columnBreak>F</columnBreak>
              <sameRowAsPrevious>F</sameRowAsPrevious>
            </field>
          </fields>
        </defaultFieldGroup>
      </fieldGroups>
      <subItems>
        <subList>
          <id>ITEMPRICE</id>
          <label>Price Levels</label>
          <visible>T</visible>
          <neverEmpty>F</neverEmpty>
        </subList>
      </subItems>
    </tab>
    <tab>
      <id>ITEMACCOUNTING</id>
      <label>Accounting</label>
      <visible>T</visible>
      <fieldGroups>
        <fieldGroup scriptid="accounts">
          <label>Cuentas</label>
          <visible>T</visible>
          <showTitle>T</showTitle>
          <singleColumn>F</singleColumn>
          <fields position="MIDDLE">
            <field>
              <id>CURRENCY</id>
              <label>Currency</label>
              <visible>T</visible>
              <mandatory>F</mandatory>
              <displayType>NORMAL</displayType>
              <columnBreak>F</columnBreak>
              <sameRowAsPrevious>F</sameRowAsPrevious>
            </field>
            <field>
              <id>COGSACCOUNT</id>
              <label>COGS Account</label>
              <visible>T</visible>
              <mandatory>F</mandatory>
              <displayType>NORMAL</displayType>
              <columnBreak>F</columnBreak>
              <sameRowAsPrevious>F</sameRowAsPrevious>
            </field>
            <field>
              <id>ASSETACCOUNT</id>
              <label>Asset Account</label>
              <visible>T</visible>
              <mandatory>F</mandatory>
              <displayType>NORMAL</displayType>
              <columnBreak>F</columnBreak>
              <sameRowAsPrevious>F</sameRowAsPrevious>
            </field>
            <field>
              <id>INCOMEACCOUNT</id>
              <label>Income Account</label>
              <visible>T</visible>
              <mandatory>F</mandatory>
              <displayType>NORMAL</displayType>
              <columnBreak>F</columnBreak>
              <sameRowAsPrevious>F</sameRowAsPrevious>
            </field>
            <field>
              <id>GAINLOSSACCOUNT</id>
              <label>Gain/Loss Account</label>
              <visible>F</visible>
              <mandatory>F</mandatory>
              <displayType>NORMAL</displayType>
              <columnBreak>T</columnBreak>
              <sameRowAsPrevious>F</sameRowAsPrevious>
            </field>
            <field>
              <id>BILLPRICEVARIANCEACCT</id>
              <label>Price Variance Account</label>
              <visible>F</visible>
              <mandatory>F</mandatory>
              <displayType>NORMAL</displayType>
              <columnBreak>F</columnBreak>
              <sameRowAsPrevious>F</sameRowAsPrevious>
            </field>
            <field>
              <id>BILLQTYVARIANCEACCT</id>
              <label>Quantity Variance Account</label>
              <visible>F</visible>
              <mandatory>F</mandatory>
              <displayType>NORMAL</displayType>
              <columnBreak>F</columnBreak>
              <sameRowAsPrevious>F</sameRowAsPrevious>
            </field>
            <field>
              <id>BILLEXCHRATEVARIANCEACCT</id>
              <label>Exchange Rate Variance Account</label>
              <visible>F</visible>
              <mandatory>F</mandatory>
              <displayType>NORMAL</displayType>
              <columnBreak>F</columnBreak>
              <sameRowAsPrevious>F</sameRowAsPrevious>
            </field>
            <field>
              <id>CUSTRETURNVARIANCEACCOUNT</id>
              <label>Customer Return Variance Account</label>
              <visible>F</visible>
              <mandatory>F</mandatory>
              <displayType>NORMAL</displayType>
              <columnBreak>T</columnBreak>
              <sameRowAsPrevious>F</sameRowAsPrevious>
            </field>
            <field>
              <id>VENDRETURNVARIANCEACCOUNT</id>
              <label>Vendor Return Variance Account</label>
              <visible>F</visible>
              <mandatory>F</mandatory>
              <displayType>NORMAL</displayType>
              <columnBreak>F</columnBreak>
              <sameRowAsPrevious>F</sameRowAsPrevious>
            </field>
          </fields>
        </fieldGroup>
        <fieldGroup scriptid="revenuerecognitionandamortization">
          <label>Reconocimiento de ingresos y amortización</label>
          <visible>T</visible>
          <showTitle>T</showTitle>
          <singleColumn>F</singleColumn>
        </fieldGroup>
        <fieldGroup scriptid="taxtariff">
          <label>Impuesto/Arancel </label>
          <visible>T</visible>
          <showTitle>T</showTitle>
          <singleColumn>F</singleColumn>
          <fields position="MIDDLE">
            <field>
              <id>TAXSCHEDULE</id>
              <label>Tax Schedule</label>
              <visible>T</visible>
              <mandatory>T</mandatory>
              <displayType>NORMAL</displayType>
              <columnBreak>F</columnBreak>
              <sameRowAsPrevious>F</sameRowAsPrevious>
            </field>
          </fields>
        </fieldGroup>
        <defaultFieldGroup/>
      </fieldGroups>
      <subItems>
        <subTab>
          <id>ITEMMATRIX</id>
          <label>Matrix Items</label>
          <visible>T</visible>
          <fieldGroups>
            <defaultFieldGroup>
              <fields position="MIDDLE">
                <field>
                  <id>MATRIXITEMNAMETEMPLATE</id>
                  <label>Matrix Item Name Template</label>
                  <visible>T</visible>
                  <mandatory>F</mandatory>
                  <displayType>NORMAL</displayType>
                  <columnBreak>F</columnBreak>
                  <sameRowAsPrevious>F</sameRowAsPrevious>
                </field>
              </fields>
            </defaultFieldGroup>
          </fieldGroups>
          <subLists/>
        </subTab>
      </subItems>
    </tab>
    <tab>
      <id>ITEMMERCHANDISEHIERARCHY</id>
      <label>Merchandise Hierarchy</label>
      <visible>T</visible>
      <fieldGroups>
        <defaultFieldGroup/>
      </fieldGroups>
      <subItems/>
    </tab>
    <tab>
      <id>ITEMRELRECORDS</id>
      <label>Related Records</label>
      <visible>T</visible>
      <fieldGroups>
        <defaultFieldGroup/>
      </fieldGroups>
      <subItems>
        <subList>
          <id>ITEMTRANSACTIONS</id>
          <label>Transactions</label>
          <visible>T</visible>
          <neverEmpty>F</neverEmpty>
        </subList>
      </subItems>
    </tab>
    <tab>
      <id>ITEMSYSTEMINFORMATION</id>
      <label>System Information</label>
      <visible>T</visible>
      <fieldGroups>
        <defaultFieldGroup>
          <fields position="MIDDLE">
            <field>
              <id>DATECONVERTEDTOINV</id>
              <label>Date Converted To Inventory</label>
              <visible>T</visible>
              <mandatory>F</mandatory>
              <displayType>NORMAL</displayType>
              <columnBreak>F</columnBreak>
              <sameRowAsPrevious>F</sameRowAsPrevious>
            </field>
            <field>
              <id>ORIGINALITEMTYPE</id>
              <label>Original Item Type</label>
              <visible>T</visible>
              <mandatory>F</mandatory>
              <displayType>NORMAL</displayType>
              <columnBreak>F</columnBreak>
              <sameRowAsPrevious>F</sameRowAsPrevious>
            </field>
            <field>
              <id>ORIGINALITEMSUBTYPE</id>
              <label>Original Item SubType</label>
              <visible>T</visible>
              <mandatory>F</mandatory>
              <displayType>NORMAL</displayType>
              <columnBreak>F</columnBreak>
              <sameRowAsPrevious>F</sameRowAsPrevious>
            </field>
          </fields>
        </defaultFieldGroup>
      </fieldGroups>
      <subItems>
        <subList>
          <id>ITEMSYSTEMNOTES</id>
          <label>System Notes</label>
          <visible>T</visible>
          <neverEmpty>F</neverEmpty>
        </subList>
        <subTab>
          <id>ITEMTRANSLATION</id>
          <label>Translation</label>
          <visible>T</visible>
          <fieldGroups>
            <defaultFieldGroup/>
          </fieldGroups>
          <subLists>
            <subList>
              <id>ITEMTRANSLATIONS</id>
              <label>Translation</label>
              <visible>T</visible>
              <neverEmpty>F</neverEmpty>
            </subList>
          </subLists>
        </subTab>
        <subList>
          <id>ITEMACTIVEWORKFLOWS</id>
          <label>Active Workflows</label>
          <visible>T</visible>
          <neverEmpty>F</neverEmpty>
        </subList>
        <subList>
          <id>ITEMWORKFLOWHISTORY</id>
          <label>Workflow History</label>
          <visible>T</visible>
          <neverEmpty>F</neverEmpty>
        </subList>
      </subItems>
    </tab>
    <tab>
      <id>ITEMHAZMATDGOODS</id>
      <label>Hazmat/Dangerous Goods</label>
      <visible>T</visible>
      <fieldGroups>
        <defaultFieldGroup/>
      </fieldGroups>
      <subItems/>
    </tab>
    <tab>
      <id>ITEMCOMMUNICATION</id>
      <label>Communication</label>
      <visible>T</visible>
      <fieldGroups>
        <defaultFieldGroup/>
      </fieldGroups>
      <subItems>
        <subList>
          <id>ITEMEVENTS</id>
          <label>Events</label>
          <visible>T</visible>
          <neverEmpty>F</neverEmpty>
        </subList>
        <subList>
          <id>ITEMTASKS</id>
          <label>Tasks</label>
          <visible>T</visible>
          <neverEmpty>F</neverEmpty>
        </subList>
        <subList>
          <id>ITEMCALLS</id>
          <label>Phone Calls</label>
          <visible>T</visible>
          <neverEmpty>F</neverEmpty>
        </subList>
        <subList>
          <id>ITEMMEDIAITEM</id>
          <label>Files</label>
          <visible>T</visible>
          <neverEmpty>F</neverEmpty>
        </subList>
        <subList>
          <id>ITEMUSERNOTES</id>
          <label>User Notes</label>
          <visible>T</visible>
          <neverEmpty>F</neverEmpty>
        </subList>
      </subItems>
    </tab>
    <tab>
      <id>ITEMSTORE</id>
      <label>Web Store</label>
      <visible>F</visible>
      <fieldGroups>
        <fieldGroup scriptid="webstoredisplay">
          <label>Visualización de tienda web</label>
          <visible>T</visible>
          <showTitle>T</showTitle>
          <singleColumn>F</singleColumn>
          <fields position="MIDDLE">
            <field>
              <id>ISONLINE</id>
              <label>Display in Web Store</label>
              <visible>T</visible>
              <mandatory>F</mandatory>
              <displayType>NORMAL</displayType>
              <columnBreak>F</columnBreak>
              <sameRowAsPrevious>F</sameRowAsPrevious>
            </field>
            <field>
              <id>PAGETITLE</id>
              <label>Page Title</label>
              <visible>T</visible>
              <mandatory>F</mandatory>
              <displayType>NORMAL</displayType>
              <columnBreak>F</columnBreak>
              <sameRowAsPrevious>F</sameRowAsPrevious>
            </field>
            <field>
              <id>STOREDISPLAYNAME</id>
              <label>Web Store Display Name</label>
              <visible>T</visible>
              <mandatory>F</mandatory>
              <displayType>NORMAL</displayType>
              <columnBreak>F</columnBreak>
              <sameRowAsPrevious>F</sameRowAsPrevious>
            </field>
            <field>
              <id>STOREDESCRIPTION</id>
              <label>Web Store Description</label>
              <visible>T</visible>
              <mandatory>F</mandatory>
              <displayType>NORMAL</displayType>
              <columnBreak>F</columnBreak>
              <sameRowAsPrevious>F</sameRowAsPrevious>
            </field>
            <field>
              <id>STOREDETAILEDDESCRIPTION</id>
              <label>Detailed Description</label>
              <visible>T</visible>
              <mandatory>F</mandatory>
              <displayType>NORMAL</displayType>
              <columnBreak>F</columnBreak>
              <sameRowAsPrevious>F</sameRowAsPrevious>
            </field>
            <field>
              <id>FEATUREDDESCRIPTION</id>
              <label>Featured Description</label>
              <visible>T</visible>
              <mandatory>F</mandatory>
              <displayType>NORMAL</displayType>
              <columnBreak>F</columnBreak>
              <sameRowAsPrevious>F</sameRowAsPrevious>
            </field>
            <field>
              <id>STOREDISPLAYIMAGE</id>
              <label>Item Display Image</label>
              <visible>T</visible>
              <mandatory>F</mandatory>
              <displayType>NORMAL</displayType>
              <columnBreak>F</columnBreak>
              <sameRowAsPrevious>F</sameRowAsPrevious>
            </field>
            <field>
              <id>STOREDISPLAYTHUMBNAIL</id>
              <label>Item Display Thumbnail</label>
              <visible>T</visible>
              <mandatory>F</mandatory>
              <displayType>NORMAL</displayType>
              <columnBreak>F</columnBreak>
              <sameRowAsPrevious>F</sameRowAsPrevious>
            </field>
          </fields>
        </fieldGroup>
        <fieldGroup scriptid="specialsdisplay">
          <label>Mostrar ofertas especiales</label>
          <visible>T</visible>
          <showTitle>T</showTitle>
          <singleColumn>F</singleColumn>
          <fields position="MIDDLE">
            <field>
              <id>ONSPECIAL</id>
              <label>On Special</label>
              <visible>T</visible>
              <mandatory>F</mandatory>
              <displayType>NORMAL</displayType>
              <columnBreak>F</columnBreak>
              <sameRowAsPrevious>F</sameRowAsPrevious>
            </field>
            <field>
              <id>SPECIALSDESCRIPTION</id>
              <label>Specials Description</label>
              <visible>T</visible>
              <mandatory>F</mandatory>
              <displayType>NORMAL</displayType>
              <columnBreak>F</columnBreak>
              <sameRowAsPrevious>F</sameRowAsPrevious>
            </field>
          </fields>
        </fieldGroup>
        <fieldGroup scriptid="stockandpricingbehavior">
          <label>Comportamiento de stock y</label>
          <visible>T</visible>
          <showTitle>T</showTitle>
          <singleColumn>F</singleColumn>
          <fields position="MIDDLE">
            <field>
              <id>ISDONATIONITEM</id>
              <label>Variable Amount</label>
              <visible>T</visible>
              <mandatory>F</mandatory>
              <displayType>NORMAL</displayType>
              <columnBreak>F</columnBreak>
              <sameRowAsPrevious>F</sameRowAsPrevious>
            </field>
            <field>
              <id>SHOWDEFAULTDONATIONAMOUNT</id>
              <label>Show Default Amount</label>
              <visible>T</visible>
              <mandatory>F</mandatory>
              <displayType>NORMAL</displayType>
              <columnBreak>F</columnBreak>
              <sameRowAsPrevious>F</sameRowAsPrevious>
            </field>
            <field>
              <id>MAXDONATIONAMOUNT</id>
              <label>Maximum Variable Amount</label>
              <visible>T</visible>
              <mandatory>F</mandatory>
              <displayType>NORMAL</displayType>
              <columnBreak>F</columnBreak>
              <sameRowAsPrevious>F</sameRowAsPrevious>
            </field>
            <field>
              <id>DONTSHOWPRICE</id>
              <label>Don't Show Price</label>
              <visible>T</visible>
              <mandatory>F</mandatory>
              <displayType>NORMAL</displayType>
              <columnBreak>F</columnBreak>
              <sameRowAsPrevious>F</sameRowAsPrevious>
            </field>
            <field>
              <id>NOPRICEMESSAGE</id>
              <label>No Price Message</label>
              <visible>T</visible>
              <mandatory>F</mandatory>
              <displayType>NORMAL</displayType>
              <columnBreak>F</columnBreak>
              <sameRowAsPrevious>F</sameRowAsPrevious>
            </field>
          </fields>
        </fieldGroup>
        <fieldGroup scriptid="searchengineandfeeds">
          <label>Motor de búsqueda y fuentes</label>
          <visible>T</visible>
          <showTitle>T</showTitle>
          <singleColumn>F</singleColumn>
          <fields position="MIDDLE">
            <field>
              <id>URLCOMPONENT</id>
              <label>URL Component</label>
              <visible>T</visible>
              <mandatory>F</mandatory>
              <displayType>NORMAL</displayType>
              <columnBreak>F</columnBreak>
              <sameRowAsPrevious>F</sameRowAsPrevious>
            </field>
            <field>
              <id>EXCLUDEFROMSITEMAP</id>
              <label>Exclude From Sitemap</label>
              <visible>T</visible>
              <mandatory>F</mandatory>
              <displayType>NORMAL</displayType>
              <columnBreak>F</columnBreak>
              <sameRowAsPrevious>F</sameRowAsPrevious>
            </field>
            <field>
              <id>SITEMAPPRIORITY</id>
              <label>Sitemap Priority</label>
              <visible>T</visible>
              <mandatory>F</mandatory>
              <displayType>NORMAL</displayType>
              <columnBreak>F</columnBreak>
              <sameRowAsPrevious>F</sameRowAsPrevious>
            </field>
          </fields>
        </fieldGroup>
        <defaultFieldGroup/>
      </fieldGroups>
      <subItems>
        <subTab>
          <id>ITEMRELITEMS</id>
          <label>Related Items</label>
          <visible>T</visible>
          <fieldGroups>
            <defaultFieldGroup>
              <fields position="MIDDLE">
                <field>
                  <id>RELATEDITEMSDESCRIPTION</id>
                  <label>Related Items Description</label>
                  <visible>T</visible>
                  <mandatory>F</mandatory>
                  <displayType>NORMAL</displayType>
                  <columnBreak>F</columnBreak>
                  <sameRowAsPrevious>F</sameRowAsPrevious>
                </field>
              </fields>
            </defaultFieldGroup>
          </fieldGroups>
          <subLists/>
        </subTab>
      </subItems>
    </tab>
    <tab>
      <id>ITEMPREFERENCES</id>
      <label>Preferences</label>
      <visible>F</visible>
      <fieldGroups>
        <defaultFieldGroup>
          <fields position="MIDDLE">
            <field>
              <id>AVAILABLETOPARTNERS</id>
              <label>Available to Adv. Partners</label>
              <visible>T</visible>
              <mandatory>F</mandatory>
              <displayType>NORMAL</displayType>
              <columnBreak>F</columnBreak>
              <sameRowAsPrevious>F</sameRowAsPrevious>
            </field>
            <field>
              <id>OFFERSUPPORT</id>
              <label>Offer Support</label>
              <visible>T</visible>
              <mandatory>F</mandatory>
              <displayType>NORMAL</displayType>
              <columnBreak>F</columnBreak>
              <sameRowAsPrevious>F</sameRowAsPrevious>
            </field>
          </fields>
        </defaultFieldGroup>
      </fieldGroups>
      <subItems/>
    </tab>
    <tab>
      <id>ITEMCUSTOM</id>
      <label>Custom</label>
      <visible>T</visible>
      <fieldGroups>
        <defaultFieldGroup>
          <fields position="MIDDLE">
            <field>
              <id>[scriptid=custitem_4601_defaultwitaxcode]</id>
              <label>Código de impuestos de retención predet</label>
              <visible>T</visible>
              <mandatory>F</mandatory>
              <displayType>NORMAL</displayType>
              <columnBreak>F</columnBreak>
              <sameRowAsPrevious>F</sameRowAsPrevious>
            </field>
          </fields>
        </defaultFieldGroup>
      </fieldGroups>
      <subItems>
        <subList>
          <id>[scriptid=customrecord_edp_price_update_sys_notes.custrecord_edp_system_notes_item]</id>
          <label>Price Update Logses</label>
          <visible>T</visible>
          <neverEmpty>F</neverEmpty>
        </subList>
      </subItems>
    </tab>
    <tab>
      <id>[scriptid=custtab_4_3838944_241]</id>
      <label>Informes de impuestos</label>
      <visible>F</visible>
      <fieldGroups>
        <defaultFieldGroup>
          <fields position="MIDDLE">
            <field>
              <id>[scriptid=custitem_un_number]</id>
              <label>Número UN</label>
              <visible>T</visible>
              <mandatory>F</mandatory>
              <displayType>NORMAL</displayType>
              <columnBreak>F</columnBreak>
              <sameRowAsPrevious>F</sameRowAsPrevious>
            </field>
          </fields>
        </defaultFieldGroup>
      </fieldGroups>
      <subItems/>
    </tab>
    <tab>
      <id>[scriptid=custtab_15_3776644_208]</id>
      <label>Tax Reporting</label>
      <visible>F</visible>
      <fieldGroups>
        <defaultFieldGroup>
          <fields position="MIDDLE">
            <field>
              <id>[scriptid=custitem_commodity_code]</id>
              <label>Código del producto</label>
              <visible>T</visible>
              <mandatory>F</mandatory>
              <displayType>NORMAL</displayType>
              <columnBreak>F</columnBreak>
              <sameRowAsPrevious>F</sameRowAsPrevious>
            </field>
            <field>
              <id>[scriptid=custitem_code_of_supply]</id>
              <label>Código de suministro</label>
              <visible>T</visible>
              <mandatory>F</mandatory>
              <displayType>NORMAL</displayType>
              <columnBreak>F</columnBreak>
              <sameRowAsPrevious>F</sameRowAsPrevious>
            </field>
            <field>
              <id>[scriptid=custitem_type_of_goods]</id>
              <label>Tipo de bienes</label>
              <visible>T</visible>
              <mandatory>F</mandatory>
              <displayType>NORMAL</displayType>
              <columnBreak>F</columnBreak>
              <sameRowAsPrevious>F</sameRowAsPrevious>
            </field>
            <field>
              <id>[scriptid=custitem_itr_supplementary_unit]</id>
              <label>Unidad suplementaria</label>
              <visible>T</visible>
              <mandatory>F</mandatory>
              <displayType>NORMAL</displayType>
              <columnBreak>F</columnBreak>
              <sameRowAsPrevious>F</sameRowAsPrevious>
            </field>
          </fields>
        </defaultFieldGroup>
      </fieldGroups>
      <subItems/>
    </tab>
    <tab>
      <id>[scriptid=custtab_5_3761957_208]</id>
      <label>Customer Part Number</label>
      <visible>T</visible>
      <fieldGroups>
        <defaultFieldGroup/>
      </fieldGroups>
      <subItems>
        <subList>
          <id>[scriptid=customrecord_scm_customerpartnumber.custrecord_scm_cpn_item]</id>
          <label>Número de parte del cliente</label>
          <visible>T</visible>
          <neverEmpty>F</neverEmpty>
        </subList>
      </subItems>
    </tab>
    <tab>
      <id>[scriptid=custtab_6_3761957_208]</id>
      <label>Landed Cost Templates</label>
      <visible>T</visible>
      <fieldGroups>
        <defaultFieldGroup/>
      </fieldGroups>
      <subItems>
        <subList>
          <id>[scriptid=customrecord_scm_lc_mapping.custrecord_scm_lc_mapping_item]</id>
          <label>Asignación de la plantilla de c</label>
          <visible>T</visible>
          <neverEmpty>F</neverEmpty>
        </subList>
      </subItems>
    </tab>
    <tab>
      <id>[scriptid=custtab_11_3761957_650]</id>
      <label>Item Substitution</label>
      <visible>T</visible>
      <fieldGroups>
        <defaultFieldGroup/>
      </fieldGroups>
      <subItems>
        <subList>
          <id>[scriptid=customrecord_scm_item_substitute.custrecord_scm_itemsub_parent]</id>
          <label>Sustituto del artículo</label>
          <visible>T</visible>
          <neverEmpty>F</neverEmpty>
        </subList>
      </subItems>
    </tab>
  </tabs>
  <quickViewFields>
    <field>
      <id>ITEMID</id>
    </field>
    <field>
      <id>DISPLAYNAME</id>
    </field>
    <field>
      <id>SALESDESCRIPTION</id>
    </field>
    <field>
      <id>PARENT</id>
    </field>
    <field>
      <id>UNITSTYPE</id>
    </field>
    <field>
      <id>RATE</id>
    </field>
    <field>
      <id>QUANTITYAVAILABLE</id>
    </field>
  </quickViewFields>
  <actionbar>
    <buttons>
      <button>
        <id>SEARCH</id>
        <label>Buscar</label>
        <visible>T</visible>
      </button>
      <button>
        <id>PRINTLABEL</id>
        <label>Imprimir etiqueta</label>
        <visible>T</visible>
      </button>
    </buttons>
    <menu>
      <menuitem>
        <id>UPDATEMATRIX</id>
        <label>Actualizar matriz</label>
        <visible>T</visible>
      </menuitem>
      <menuitem>
        <id>ADDMATRIX</id>
        <label>Agregar artículos</label>
        <visible>T</visible>
      </menuitem>
      <menuitem>
        <id>CREATEMATRIX</id>
        <label>Crear matriz</label>
        <visible>T</visible>
      </menuitem>
      <menuitem>
        <id>DELETE</id>
        <label>Eliminar</label>
        <visible>T</visible>
      </menuitem>
      <menuitem>
        <id>SUBMITAS</id>
        <label>Guardar como</label>
        <visible>T</visible>
      </menuitem>
      <menuitem>
        <id>SUBMITNEW</id>
        <label>Guardar y nuevo</label>
        <visible>T</visible>
      </menuitem>
      <menuitem>
        <id>NEW</id>
        <label>Nuevo</label>
        <visible>T</visible>
      </menuitem>
      <menuitem>
        <id>REMOVEMATRIXOPTIONS</id>
        <label>Quitar opciones de matriz</label>
        <visible>T</visible>
      </menuitem>
      <menuitem>
        <id>MAKECOPY</id>
        <label>Realizar copia</label>
        <visible>T</visible>
      </menuitem>
      <menuitem>
        <id>VIEWALLTRANSACTIONS</id>
        <label>Ver todas las transacciones</label>
        <visible>T</visible>
      </menuitem>
    </menu>
  </actionbar>
  <editingInList>T</editingInList>
</entryForm>
